pris/__init__.py
pris/frames.py
pris/hot.py
pris/insert.py
pris/printing.py
pris/sequence.py
pris/sequences.py
pris-0.5.dist-info/METADATA
pris-0.5.dist-info/WHEEL
pris-0.5.dist-info/licenses/LICENSE
pris-0.5.dist-info/RECORD
