Metadata-Version: 2.4
Name: pris
Version: 0.5
Summary: PRIS - pattern recognition integer sequence. Detect patterns or sequences in data streams.
Project-URL: Documentation, https://github.com/Strangemother/python-pris#readme
Project-URL: Homepage, https://github.com/Strangemother/python-pris
Project-URL: Repository, https://github.com/Strangemother/python-pris
Project-URL: Issues, https://github.com/Strangemother/python-pris/issues
Author-email: Strangemother <pris@strangemother.com>
License-Expression: MIT
License-File: LICENSE
Classifier: Development Status :: 4 - Beta
Classifier: Programming Language :: Python
Classifier: Programming Language :: Python :: 3.8
Classifier: Programming Language :: Python :: 3.9
Classifier: Programming Language :: Python :: 3.10
Classifier: Programming Language :: Python :: 3.11
Classifier: Programming Language :: Python :: 3.12
Classifier: Programming Language :: Python :: Implementation :: CPython
Classifier: Programming Language :: Python :: Implementation :: PyPy
Requires-Python: >=3.8
